[
  {
    "text": "A new Apple Watch has at least one new built-in app because of an exclusive feature not found on existing watches",
    "full-pick-text": "A new Apple Watch has at least one new built-in app because of an exclusive feature not found on existing watches",
    "notes": "",
    "game": "2020 September Rickies",
    "type": "Ricky",
    "topics": [
      "Apple Apps",
      "Apple Watch",
      "Live Edited"
    ],
    "host": "Federico",
    "pick-conditions": 2,
    "score": 2,
    "overcast-graded": "https://overcast.fm/+FXx5peDck/49:49",
    "overcast-picked": "https://overcast.fm/+FXx5XgcdI/1:23:32"
  },
  {
    "text": "Apple introduces a new, lower end Apple Watch model in addition to the higher end Series 6",
    "full-pick-text": "Apple introduces a new, lower end Apple Watch model in addition to the higher end Series 6",
    "notes": "",
    "game": "2020 September Rickies",
    "type": "Regular",
    "topics": [
      "Apple Watch",
      "Live Edited"
    ],
    "host": "Federico",
    "pick-conditions": 2,
    "score": 1,
    "overcast-graded": "https://overcast.fm/+FXx5peDck/41:32",
    "overcast-picked": "https://overcast.fm/+FXx5XgcdI/1:03:12"
  },
  {
    "text": "Apple unveils a new Apple Watch",
    "full-pick-text": "Apple unveils a new Apple Watch",
    "notes": "<p><ul><li>While Federico had some criticism of <a class=\"tc-tiddlylink tc-tiddlylink-resolves\" href=\"#The%20iPad%20home%20screen%20gets%20new%20features\">a couple</a> of <a class=\"tc-tiddlylink tc-tiddlylink-resolves\" href=\"#Memoji%20will%20get%20updated%20to%20include%20face%20coverings\">Myke's picks</a> in <a class=\"tc-tiddlylink tc-tiddlylink-resolves\" href=\"#2020%20Summer%20Rickies\">the previous game</a> along the same lines, this was the very first time that Federico specifically called out a lack of \"passion\" in a pick.</li></ul></p>",
    "game": "2020 September Rickies",
    "type": "Regular",
    "topics": [
      "Apple Watch",
      "No Passion"
    ],
    "host": "Myke",
    "pick-conditions": 1,
    "score": 1,
    "overcast-graded": "https://overcast.fm/+FXx5peDck/12:32",
    "overcast-picked": "https://overcast.fm/+FXx5XgcdI/46:25"
  },
  {
    "text": "Apple Watch SE is not updated, but receives a price cut",
    "full-pick-text": "Apple Watch SE is not updated, but receives a price cut",
    "notes": "<p><ul><li>\"Currently $249/$299 for GPS, $279/$329 for cellular\"</li></ul></p>",
    "game": "2023 September Rickies",
    "type": "Flexie",
    "topics": [
      "Apple Watch",
      "Buzzkill"
    ],
    "host": "Stephen",
    "pick-conditions": 2,
    "overcast-picked": "https://overcast.fm/+FXx5s-OzI/1:13:15"
  },
  {
    "text": "Apple Watch Ultra 2 comes in at least 1 new finish",
    "full-pick-text": "Apple Watch Ultra 2 comes in at least 1 new finish",
    "notes": "",
    "game": "2023 September Rickies",
    "type": "Flexie",
    "topics": [
      "Apple Watch"
    ],
    "host": "Stephen",
    "pick-conditions": 2,
    "overcast-picked": "https://overcast.fm/+FXx5s-OzI/1:13:43"
  },
  {
    "text": "Apple Watch with an always-on display",
    "full-pick-text": "Apple Watch with an always-on display",
    "notes": "<p><ul><li>The Series 5 watch added this feature in 2019.</li></ul></p>",
    "game": "2018 Annual Predictions",
    "type": "Regular",
    "topics": [
      "Ahead of Its Time",
      "Apple Watch"
    ],
    "host": "Myke",
    "pick-conditions": 1,
    "score": 0,
    "ahead-by": 252,
    "overcast-graded": "https://overcast.fm/+FXx495ZrA/05:03",
    "overcast-picked": "https://overcast.fm/+FXx5giTnQ/35:08"
  },
  {
    "text": "At least one new watchOS feature or app is introduced alongside the new Apple Watch",
    "full-pick-text": "At least one new watchOS feature or app is introduced alongside the new Apple Watch",
    "notes": "",
    "game": "2022 September Rickies",
    "type": "Flexie",
    "topics": [
      "Apple Watch"
    ],
    "host": "Federico",
    "pick-conditions": 1,
    "score": 1,
    "overcast-graded": "https://overcast.fm/+FXx650Foc/1:25:15",
    "overcast-picked": "https://overcast.fm/+FXx4UJ2RE/1:35:50"
  },
  {
    "text": "Bands for the new Apple Watch \"Pro\" are not backward compatible with other Apple Watches",
    "full-pick-text": "Bands for the new Apple Watch \"Pro\" are not backward compatible with other Apple Watches",
    "notes": "<p><ul><li><a href=\"https://9to5mac.com/2022/09/07/apple-watch-ultra-band-compatibility-explained/\" target=\"_blank\">It does appear to be compatible</a> at the time of grading.</li></ul></p>",
    "game": "2022 September Rickies",
    "type": "Flexie",
    "topics": [
      "Apple Watch",
      "Buzzkill",
      "Unvindicatable"
    ],
    "host": "Federico",
    "pick-conditions": 1,
    "score": 0,
    "overcast-graded": "https://overcast.fm/+FXx650Foc/1:29:12",
    "overcast-picked": "https://overcast.fm/+FXx4UJ2RE/1:39:28"
  },
  {
    "text": "New Apple Watch is a 'Series 8' Watch",
    "full-pick-text": "New Apple Watch is a 'Series 8' Watch",
    "notes": "<p><ul><li>\"It may 'technically' be an Edition, but no new name (like Pro or Max)\"</li><li>As mentioned in <a href=\"https://upgrade.cards/card/apple092022\" target=\"_blank\">the Upgrade Draft earlier in the week</a>, but not chosen there. This was deemed insufficiently Risky, and so was demoted to a Flexie.</li></ul></p>",
    "game": "2022 September Rickies",
    "type": "Flexie",
    "topics": [
      "Alternate Risky",
      "Apple Watch",
      "Unvindicatable"
    ],
    "host": "Myke",
    "pick-conditions": 1,
    "score": 0,
    "overcast-graded": "https://overcast.fm/+FXx650Foc/1:21:44",
    "overcast-picked": "https://overcast.fm/+FXx4UJ2RE/1:31:43"
  },
  {
    "text": "New Apple Watch is not a part of the presentation",
    "full-pick-text": "New Apple Watch is not a part of the presentation",
    "notes": "",
    "game": "2021 September Rickies",
    "type": "Flexie",
    "topics": [
      "Apple Watch",
      "Buzzkill",
      "Unvindicatable"
    ],
    "host": "Myke",
    "pick-conditions": 1,
    "score": 0,
    "overcast-graded": "https://overcast.fm/+FXx6z4vdc/1:08:13",
    "overcast-picked": "https://overcast.fm/+FXx5Crqo4/1:11:07"
  },
  {
    "text": "New Apple Watch Ultra band style",
    "full-pick-text": "New Apple Watch Ultra band style",
    "notes": "",
    "game": "2023 September Rickies",
    "type": "Flexie",
    "topics": [
      "Accessories",
      "Apple Watch"
    ],
    "host": "Myke",
    "pick-conditions": 1,
    "overcast-picked": "https://overcast.fm/+FXx5s-OzI/1:17:45"
  },
  {
    "text": "New iPhone case colors and/or watch band colors are introduced at or after the event",
    "full-pick-text": "New iPhone case colors and/or watch band colors are introduced at or after the event",
    "notes": "",
    "game": "2022 March Rickies",
    "type": "Regular",
    "topics": [
      "iPhone",
      "Accessories",
      "Apple Watch"
    ],
    "host": "Federico",
    "pick-conditions": 1,
    "score": 1,
    "overcast-graded": "https://overcast.fm/+FXx4aVfvI/23:36",
    "overcast-picked": "https://overcast.fm/+FXx4VfMWE/31:20"
  },
  {
    "text": "New watch bands",
    "full-pick-text": "New watch bands",
    "notes": "",
    "game": "2018 iPhone Event Predictions",
    "type": "NonGraded",
    "topics": [
      "Apple Watch"
    ],
    "host": "Federico",
    "pick-conditions": 1,
    "score": 1,
    "overcast-graded": "https://overcast.fm/+FXx5Kx09c/1:24:46",
    "overcast-picked": "https://overcast.fm/+FXx4E3x_I/46:18"
  },
  {
    "text": "No iPads, iPhone and Apple Watch only",
    "full-pick-text": "No iPads, iPhone and Apple Watch only",
    "notes": "",
    "game": "2018 iPhone Event Predictions",
    "type": "NonGraded",
    "topics": [
      "iPhone",
      "iPad",
      "Apple Watch",
      "Buzzkill"
    ],
    "host": "Stephen",
    "pick-conditions": 3,
    "score": 1,
    "overcast-graded": "https://overcast.fm/+FXx5Kx09c/1:25:29",
    "overcast-picked": "https://overcast.fm/+FXx4E3x_I/55:57"
  },
  {
    "text": "No specific preorder date is set for the Apple Watch",
    "full-pick-text": "No specific preorder date is set for the Apple Watch",
    "notes": "",
    "game": "2021 September Rickies",
    "type": "Flexie",
    "topics": [
      "Apple Watch"
    ],
    "host": "Stephen",
    "pick-conditions": 1,
    "score": 1,
    "overcast-graded": "https://overcast.fm/+FXx6z4vdc/1:10:39",
    "overcast-picked": "https://overcast.fm/+FXx5Crqo4/1:17:41"
  },
  {
    "text": "Satellite communication features for iPhone and/or Apple Watch",
    "full-pick-text": "Satellite communication features for iPhone and/or Apple Watch",
    "notes": "",
    "game": "2022 September Rickies",
    "type": "Flexie",
    "topics": [
      "iPhone",
      "Apple Watch"
    ],
    "host": "Myke",
    "pick-conditions": 1,
    "score": 1,
    "overcast-graded": "https://overcast.fm/+FXx650Foc/1:18:31",
    "overcast-picked": "https://overcast.fm/+FXx4UJ2RE/1:30:32"
  },
  {
    "text": "Series 4 has multiple changes to watch faces",
    "full-pick-text": "Series 4 has multiple changes to watch faces",
    "notes": "<p><ul><li>\"(beyond the leaked ones we have already seen)\"</li></ul></p>",
    "game": "2018 iPhone Event Predictions",
    "type": "NonGraded",
    "topics": [
      "Apple Watch"
    ],
    "host": "Federico",
    "pick-conditions": 2,
    "score": 1,
    "overcast-graded": "https://overcast.fm/+FXx5Kx09c/1:24:49",
    "overcast-picked": "https://overcast.fm/+FXx4E3x_I/46:42"
  },
  {
    "text": "Someone is wearing the new Apple Watch while riding a skateboard",
    "full-pick-text": "Someone is wearing the new Apple Watch while riding a skateboard",
    "notes": "<p><ul><li>A reference to the \"Apple Watch Extreme\" rumors. Maybe Tony Hawk?</li></ul></p>",
    "game": "2022 September Rickies",
    "type": "Flexie",
    "topics": [
      "Apple Watch",
      "Stagecraft",
      "Unvindicatable"
    ],
    "host": "Myke",
    "pick-conditions": 2,
    "score": 0,
    "overcast-graded": "https://overcast.fm/+FXx650Foc/1:22:29",
    "overcast-picked": "https://overcast.fm/+FXx4UJ2RE/1:32:42"
  },
  {
    "text": "The Apple Watch moves to 5G networking",
    "full-pick-text": "The Apple Watch moves to 5G networking",
    "notes": "",
    "game": "2021 September Rickies",
    "type": "Flexie",
    "topics": [
      "Apple Watch",
      "Possible Vindication"
    ],
    "host": "Stephen",
    "pick-conditions": 1,
    "score": 0,
    "overcast-graded": "https://overcast.fm/+FXx6z4vdc/1:10:00",
    "overcast-picked": "https://overcast.fm/+FXx5Crqo4/1:14:43"
  },
  {
    "text": "The Apple Watch SE gets a price cut",
    "full-pick-text": "The Apple Watch SE gets a price cut",
    "notes": "<p><ul><li><a href=\"https://www.apple.com/newsroom/2022/09/apple-reveals-apple-watch-series-8-and-the-new-apple-watch-se/\" target=\"_blank\">Next year's model would</a>, but not this year's.</li></ul></p>",
    "game": "2021 September Rickies",
    "type": "Regular",
    "topics": [
      "Ahead of Its Time",
      "Apple Watch",
      "Passionate"
    ],
    "host": "Stephen",
    "pick-conditions": 1,
    "score": 0,
    "ahead-by": 356,
    "overcast-graded": "https://overcast.fm/+FXx6z4vdc/42:32",
    "overcast-picked": "https://overcast.fm/+FXx5Crqo4/40:31"
  },
  {
    "text": "The Apple Watch SE, announced in 2020, moves down in price with no feature changes",
    "full-pick-text": "The Apple Watch SE, announced in 2020, moves down in price with no feature changes",
    "notes": "<p><ul><li>Not graded: Series 7 or SE 2 takes the middle price point where the SE is now</li></ul></p>",
    "game": "2022 September Rickies",
    "type": "Regular",
    "topics": [
      "Apple Watch",
      "Buzzkill",
      "Unvindicatable"
    ],
    "host": "Stephen",
    "pick-conditions": 2,
    "score": 0,
    "overcast-graded": "https://overcast.fm/+FXx650Foc/48:40",
    "overcast-picked": "https://overcast.fm/+FXx4UJ2RE/44:42"
  },
  {
    "text": "The Apple Watch Series 6 uses the Series 4 & 5 design",
    "full-pick-text": "The Apple Watch Series 6 uses the Series 4 & 5 design",
    "notes": "",
    "game": "2020 September Rickies",
    "type": "Regular",
    "topics": [
      "Apple Watch"
    ],
    "host": "Stephen",
    "pick-conditions": 1,
    "score": 1,
    "overcast-graded": "https://overcast.fm/+FXx5peDck/13:43",
    "overcast-picked": "https://overcast.fm/+FXx5XgcdI/48:40"
  },
  {
    "text": "The new high-end Apple Watch is named the \"Apple Watch Pro\"",
    "full-pick-text": "The new high-end Apple Watch is named the \"Apple Watch Pro\"",
    "notes": "",
    "game": "2022 September Rickies",
    "type": "Flexie",
    "topics": [
      "Apple Watch",
      "Possible Vindication"
    ],
    "host": "Stephen",
    "pick-conditions": 1,
    "score": 0,
    "overcast-graded": "https://overcast.fm/+FXx650Foc/1:12:31",
    "overcast-picked": "https://overcast.fm/+FXx4UJ2RE/1:27:53"
  },
  {
    "text": "The next generation Apple Watch will have some kind of body temperature sensor",
    "full-pick-text": "The next generation Apple Watch will have some kind of body temperature sensor",
    "notes": "",
    "game": "2022 Annual Rickies",
    "type": "Regular",
    "topics": [
      "Apple Watch"
    ],
    "host": "Federico",
    "pick-conditions": 1,
    "score": 1,
    "overcast-graded": "https://overcast.fm/+FXx5wv1as/14:57",
    "overcast-picked": "https://overcast.fm/+FXx6bXcOY/1:16:54"
  },
  {
    "text": "The removal of Force Touch on watchOS is framed as the inclusion of Haptic Touch",
    "full-pick-text": "The removal of Force Touch on watchOS is framed as the inclusion of Haptic Touch",
    "notes": "",
    "game": "2020 September Rickies",
    "type": "Flexie",
    "topics": [
      "Apple Watch",
      "Live Edited",
      "Stagecraft",
      "Unvindicatable"
    ],
    "host": "Stephen",
    "pick-conditions": 1,
    "score": 0,
    "overcast-graded": "https://overcast.fm/+FXx5peDck/1:04:12",
    "overcast-picked": "https://overcast.fm/+FXx5XgcdI/1:32:33"
  },
  {
    "text": "There is a ceramic Apple Watch",
    "full-pick-text": "There is a ceramic Apple Watch",
    "notes": "",
    "game": "2021 September Rickies",
    "type": "Flexie",
    "topics": [
      "Apple Watch",
      "Possible Vindication"
    ],
    "host": "Myke",
    "pick-conditions": 1,
    "score": 0,
    "overcast-graded": "https://overcast.fm/+FXx6z4vdc/1:03:04",
    "overcast-picked": "https://overcast.fm/+FXx5Crqo4/1:08:32"
  },
  {
    "text": "There is no second generation Apple Watch Ultra this year",
    "full-pick-text": "There is no second generation Apple Watch Ultra this year",
    "notes": "",
    "game": "2023 Annual Rickies",
    "type": "Flexie",
    "topics": [
      "Apple Watch",
      "Buzzkill"
    ],
    "host": "Federico",
    "pick-conditions": 1,
    "overcast-picked": "https://overcast.fm/+FXx5wv1as/1:16:34"
  },
  {
    "text": "watchOS 10 gets widgets",
    "full-pick-text": "watchOS 10 gets widgets",
    "notes": "<p><ul><li>Was originally \"A widget-like interface comes to the Apple Watch\" before some workshopping.</li></ul></p>",
    "game": "2023 WWDC Rickies",
    "type": "Regular",
    "topics": [
      "Apple Watch",
      "Live Edited"
    ],
    "host": "Myke",
    "pick-conditions": 1,
    "score": 1,
    "overcast-graded": "https://overcast.fm/+FXx5Das8Q/18:47",
    "overcast-picked": "https://overcast.fm/+FXx6N6Rqw/30:03"
  },
  {
    "text": "watchOS 7 gets a software feature we haven't seen yet",
    "full-pick-text": "watchOS 7 gets a software feature we haven't seen yet",
    "notes": "",
    "game": "2020 September Rickies",
    "type": "Flexie",
    "topics": [
      "Apple Watch"
    ],
    "host": "Myke",
    "pick-conditions": 1,
    "score": 1,
    "overcast-graded": "https://overcast.fm/+FXx5peDck/1:00:38",
    "overcast-picked": "https://overcast.fm/+FXx5XgcdI/1:31:00"
  },
  {
    "text": "watchOS 7 will feature mental health features",
    "full-pick-text": "watchOS 7 will feature mental health features",
    "notes": "<p><ul><li>watchOS 8 later added a Mindfulness app, expanding on the old Breathe app.</li></ul></p>",
    "game": "2020 Summer Rickies",
    "type": "NonGraded",
    "topics": [
      "Ahead of Its Time",
      "Apple Watch"
    ],
    "host": "Federico",
    "pick-conditions": 1,
    "score": 0,
    "ahead-by": 350,
    "overcast-graded": "https://overcast.fm/+FXx7KvDUI/45:27",
    "overcast-picked": "https://overcast.fm/+FXx7FoU8U/1:20:23"
  },
  {
    "text": "watchOS gets new sleep tracking features",
    "full-pick-text": "watchOS gets new sleep tracking features",
    "notes": "",
    "game": "2020 Summer Rickies",
    "type": "Regular",
    "topics": [
      "Apple Watch"
    ],
    "host": "Federico",
    "pick-conditions": 1,
    "score": 1,
    "overcast-graded": "https://overcast.fm/+FXx7KvDUI/33:12",
    "overcast-picked": "https://overcast.fm/+FXx7FoU8U/50:29"
  }
]
