{
  "text": "Apple unveils a new high-end audio product",
  "full-pick-text": "Apple unveils a new high-end audio product",
  "notes": "<p><ul><li>\"As defined by a price of over $399, or it's a stand-alone DAC.\"</li><li>The idea of an official Apple DAC sparks a <i>lot</i> of discussion.</li></ul></p>",
  "game": "2021 WWDC Rickies",
  "type": "Ricky",
  "topics": [
    "Accessories",
    "Live Edited",
    "Possible Vindication"
  ],
  "host": "Stephen",
  "pick-conditions": 1,
  "score": -1,
  "overcast-graded": "https://overcast.fm/+FXx70G0aw/1:06:55",
  "overcast-picked": "https://overcast.fm/+FXx4EWu_4/1:20:25"
}
