{
  "text": "New Apple Watch is a 'Series 8' Watch",
  "notes": "<p><ul><li>\"It may 'technically' be an Edition, but no new name (like Pro or Max)\"</li><li>As mentioned in <a href=\"https://upgrade.cards/card/apple092022\" target=\"_blank\">the Upgrade Draft earlier in the week</a>, but not chosen there. This was deemed insufficiently Risky, and so was demoted to a Flexie.</li></ul></p>",
  "game": "2022 September Rickies",
  "type": "Flexie",
  "topics": [
    "Alternate Risky",
    "Apple Watch",
    "Unvindicatable"
  ],
  "host": "Myke",
  "pick-conditions": 1,
  "score": 0,
  "overcast-graded": "https://overcast.fm/+FXx650Foc/1:21:44",
  "overcast-picked": "https://overcast.fm/+FXx4UJ2RE/1:31:43"
}
