{
  "text": "At least two of Apple's first-party apps escape iPad compatibility mode on visionOS to become full-blown native apps",
  "full-pick-text": "At least two of Apple's first-party apps escape iPad compatibility mode on visionOS to become full-blown native apps",
  "notes": "",
  "game": "2024 WWDC Rickies",
  "type": "Flexie",
  "topics": [
    "Apple Vision Pro",
    "visionOS"
  ],
  "host": "Stephen",
  "pick-conditions": 2,
  "overcast-picked": "https://overcast.fm/+FXx56qHEU/01:12:31"
}
